howler/__init__.py
howler/actions/__init__.py
howler/actions/add_label.py
howler/actions/add_to_bundle.py
howler/actions/change_field.py
howler/actions/demote.py
howler/actions/example_plugin.py
howler/actions/prioritization.py
howler/actions/promote.py
howler/actions/remove_from_bundle.py
howler/actions/remove_label.py
howler/actions/transition.py
howler/api/__init__.py
howler/api/base.py
howler/api/socket.py
howler/api/v1/__init__.py
howler/api/v1/action.py
howler/api/v1/analytic.py
howler/api/v1/auth.py
howler/api/v1/clue.py
howler/api/v1/configs.py
howler/api/v1/dossier.py
howler/api/v1/help.py
howler/api/v1/hit.py
howler/api/v1/notebook.py
howler/api/v1/overview.py
howler/api/v1/search.py
howler/api/v1/template.py
howler/api/v1/tool.py
howler/api/v1/user.py
howler/api/v1/utils/__init__.py
howler/api/v1/utils/etag.py
howler/api/v1/view.py
howler/app.py
howler/common/README.md
howler/common/__init__.py
howler/common/classification.py
howler/common/classification.yml
howler/common/exceptions.py
howler/common/loader.py
howler/common/logging/__init__.py
howler/common/logging/audit.py
howler/common/logging/format.py
howler/common/net.py
howler/common/net_static.py
howler/common/random_user.py
howler/common/swagger.py
howler/config.py
howler/cronjobs/__init__.py
howler/cronjobs/retention.py
howler/cronjobs/rules.py
howler/cronjobs/view_cleanup.py
howler/datastore/README.md
howler/datastore/__init__.py
howler/datastore/bulk.py
howler/datastore/collection.py
howler/datastore/constants.py
howler/datastore/exceptions.py
howler/datastore/howler_store.py
howler/datastore/migrations/fix_process.py
howler/datastore/operations.py
howler/datastore/schemas.py
howler/datastore/store.py
howler/datastore/support/__init__.py
howler/datastore/support/build.py
howler/datastore/support/schemas.py
howler/datastore/types.py
howler/error.py
howler/external/__init__.py
howler/external/generate_mitre.py
howler/external/generate_sigma_rules.py
howler/external/generate_tlds.py
howler_api-3.0.0.372.dist-info/METADATA
howler_api-3.0.0.372.dist-info/WHEEL
howler_api-3.0.0.372.dist-info/entry_points.txt
howler_api-3.0.0.372.dist-info/RECORD
